[
  {
    "status": "complete",
    "type": "free_agent",
    "metadata": null,
    "created": 1641137668841,
    "settings": null,
    "leg": 17,
    "draft_picks": [],
    "creator": "603431474020032512",
    "transaction_id": "783391798759460864",
    "adds": {
      "7533": 1
    },
    "consenter_ids": [
      1
    ],
    "drops": {
      "2251": 1
    },
    "roster_ids": [
      1
    ],
    "status_updated": 1641137668841,
    "waiver_budget": []
  },
  {
    "status": "complete",
    "type": "free_agent",
    "metadata": null,
    "created": 1641008173575,
    "settings": null,
    "leg": 17,
    "draft_picks": [],
    "creator": "673623361460477952",
    "transaction_id": "782848656247275520",
    "adds": {
      "7083": 6
    },
    "consenter_ids": [
      6
    ],
    "drops": {
      "7066": 6
    },
    "roster_ids": [
      6
    ],
    "status_updated": 1641008173575,
    "waiver_budget": []
  },
  {
    "status": "complete",
    "type": "free_agent",
    "metadata": null,
    "created": 1640981352193,
    "settings": null,
    "leg": 17,
    "draft_picks": [],
    "creator": "676870999764983808",
    "transaction_id": "782736159217491968",
    "adds": {
      "7581": 7
    },
    "consenter_ids": [
      7
    ],
    "drops": {
      "3163": 7
    },
    "roster_ids": [
      7
    ],
    "status_updated": 1640981352193,
    "waiver_budget": []
  },
  {
    "status": "complete",
    "type": "free_agent",
    "metadata": null,
    "created": 1640981294949,
    "settings": null,
    "leg": 17,
    "draft_picks": [],
    "creator": "603431474020032512",
    "transaction_id": "782735919118716928",
    "adds": {
      "5121": 1
    },
    "consenter_ids": [
      1
    ],
    "drops": {
      "7581": 1
    },
    "roster_ids": [
      1
    ],
    "status_updated": 1640981294949,
    "waiver_budget": []
  },
  {
    "status": "complete",
    "type": "free_agent",
    "metadata": null,
    "created": 1640967132289,
    "settings": null,
    "leg": 17,
    "draft_picks": [],
    "creator": "603431474020032512",
    "transaction_id": "782676516617216000",
    "adds": {
      "7581": 1
    },
    "consenter_ids": [
      1
    ],
    "drops": {
      "3155": 1
    },
    "roster_ids": [
      1
    ],
    "status_updated": 1640967132289,
    "waiver_budget": []
  },
  {
    "status": "complete",
    "type": "free_agent",
    "metadata": null,
    "created": 1640802540009,
    "settings": null,
    "leg": 17,
    "draft_picks": [],
    "creator": "676870999764983808",
    "transaction_id": "781986166558879744",
    "adds": {
      "3163": 7
    },
    "consenter_ids": [
      7
    ],
    "drops": {
      "6822": 7
    },
    "roster_ids": [
      7
    ],
    "status_updated": 1640802540009,
    "waiver_budget": []
  },
  {
    "status": "complete",
    "type": "free_agent",
    "metadata": null,
    "created": 1640800425071,
    "settings": null,
    "leg": 17,
    "draft_picks": [],
    "creator": "673623361460477952",
    "transaction_id": "781977295865925632",
    "adds": {
      "5185": 6
    },
    "consenter_ids": [
      6
    ],
    "drops": {
      "5549": 6
    },
    "roster_ids": [
      6
    ],
    "status_updated": 1640800425071,
    "waiver_budget": []
  },
  {
    "status": "complete",
    "type": "free_agent",
    "metadata": null,
    "created": 1640800260492,
    "settings": null,
    "leg": 17,
    "draft_picks": [],
    "creator": "673623361460477952",
    "transaction_id": "781976605571555328",
    "adds": {
      "7066": 6
    },
    "consenter_ids": [
      6
    ],
    "drops": {
      "5185": 6
    },
    "roster_ids": [
      6
    ],
    "status_updated": 1640800260492,
    "waiver_budget": []
  },
  {
    "status": "complete",
    "type": "free_agent",
    "metadata": null,
    "created": 1640783930255,
    "settings": null,
    "leg": 17,
    "draft_picks": [],
    "creator": "673623361460477952",
    "transaction_id": "781908111593168896",
    "adds": {
      "5185": 6
    },
    "consenter_ids": [
      6
    ],
    "drops": {
      "5284": 6
    },
    "roster_ids": [
      6
    ],
    "status_updated": 1640783930255,
    "waiver_budget": []
  }
]