[{"date": "2020-04-01", "sf_trade_value": 420.0}, {"date": "2020-04-08", "sf_trade_value": 263.0}, {"date": "2020-04-15", "sf_trade_value": 303.0}, {"date": "2020-04-22", "sf_trade_value": 363.0}, {"date": "2020-04-29", "sf_trade_value": 324.0}, {"date": "2020-05-06", "sf_trade_value": 324.0}, {"date": "2020-05-13", "sf_trade_value": 324.0}, {"date": "2020-05-20", "sf_trade_value": 364.0}, {"date": "2020-05-27", "sf_trade_value": 345.0}, {"date": "2020-06-03", "sf_trade_value": 345.0}, {"date": "2020-06-10", "sf_trade_value": 364.0}, {"date": "2020-06-17", "sf_trade_value": 324.0}, {"date": "2020-06-24", "sf_trade_value": 344.0}, {"date": "2020-07-01", "sf_trade_value": 384.0}, {"date": "2020-07-08", "sf_trade_value": 344.0}, {"date": "2020-07-15", "sf_trade_value": 324.0}, {"date": "2020-07-22", "sf_trade_value": 304.0}, {"date": "2020-07-29", "sf_trade_value": 364.0}, {"date": "2020-08-05", "sf_trade_value": 305.0}, {"date": "2020-08-12", "sf_trade_value": 345.0}, {"date": "2020-08-19", "sf_trade_value": 345.0}, {"date": "2020-08-26", "sf_trade_value": 305.0}, {"date": "2020-09-02", "sf_trade_value": 264.0}, {"date": "2020-09-09", "sf_trade_value": 324.0}, {"date": "2020-09-16", "sf_trade_value": 324.0}, {"date": "2020-09-19", "sf_trade_value": 324}, {"date": "2020-09-23", "sf_trade_value": 324.0}, {"date": "2020-09-30", "sf_trade_value": 285.0}, {"date": "2020-10-07", "sf_trade_value": 284.0}, {"date": "2020-10-14", "sf_trade_value": 245.0}, {"date": "2020-10-21", "sf_trade_value": 165.0}, {"date": "2020-10-28", "sf_trade_value": 185.0}, {"date": "2020-11-04", "sf_trade_value": 187.0}, {"date": "2020-11-11", "sf_trade_value": 287.0}, {"date": "2020-11-18", "sf_trade_value": 327.0}, {"date": "2020-11-25", "sf_trade_value": 247.0}, {"date": "2020-12-02", "sf_trade_value": 167.0}, {"date": "2020-12-09", "sf_trade_value": 107.0}, {"date": "2020-12-16", "sf_trade_value": 87.0}, {"date": "2020-12-23", "sf_trade_value": 167.0}, {"date": "2020-12-30", "sf_trade_value": 187.0}, {"date": "2021-01-06", "sf_trade_value": 213.0}, {"date": "2021-01-13", "sf_trade_value": 213.0}, {"date": "2021-01-17", "sf_trade_value": 214}, {"date": "2021-01-20", "sf_trade_value": 234.0}, {"date": "2021-01-27", "sf_trade_value": 233.0}, {"date": "2021-02-03", "sf_trade_value": 373.0}, {"date": "2021-02-10", "sf_trade_value": 432.0}, {"date": "2021-02-17", "sf_trade_value": 592.0}, {"date": "2021-02-24", "sf_trade_value": 597.0}, {"date": "2021-03-03", "sf_trade_value": 597.0}, {"date": "2021-03-10", "sf_trade_value": 736.0}, {"date": "2021-03-17", "sf_trade_value": 697.0}, {"date": "2021-03-24", "sf_trade_value": 438.0}, {"date": "2021-03-31", "sf_trade_value": 398.0}, {"date": "2021-04-07", "sf_trade_value": 438.0}, {"date": "2021-04-14", "sf_trade_value": 439.0}, {"date": "2021-04-15", "sf_trade_value": 439.0}, {"date": "2021-10-19", "sf_trade_value": 64}]