[{"date": "2020-09-23", "sf_trade_value": 979.0}, {"date": "2020-09-30", "sf_trade_value": 994.0}, {"date": "2020-10-07", "sf_trade_value": 1347.0}, {"date": "2020-10-14", "sf_trade_value": 1497.0}, {"date": "2020-10-21", "sf_trade_value": 1238.0}, {"date": "2020-10-28", "sf_trade_value": 1220.0}, {"date": "2020-11-04", "sf_trade_value": 1701.0}, {"date": "2020-11-11", "sf_trade_value": 1520.0}, {"date": "2020-11-18", "sf_trade_value": 1245.0}, {"date": "2020-11-25", "sf_trade_value": 1240.0}, {"date": "2020-12-02", "sf_trade_value": 1122.0}, {"date": "2020-12-09", "sf_trade_value": 867.0}, {"date": "2020-12-16", "sf_trade_value": 854.0}, {"date": "2020-12-23", "sf_trade_value": 794.0}, {"date": "2020-12-30", "sf_trade_value": 896.0}, {"date": "2021-01-06", "sf_trade_value": 837.0}, {"date": "2021-01-13", "sf_trade_value": 960.0}, {"date": "2021-01-20", "sf_trade_value": 1041.0}, {"date": "2021-01-27", "sf_trade_value": 1337.0}, {"date": "2021-02-03", "sf_trade_value": 1621.0}, {"date": "2021-02-10", "sf_trade_value": 1691.0}, {"date": "2021-02-17", "sf_trade_value": 1693.0}, {"date": "2021-02-24", "sf_trade_value": 1684.0}, {"date": "2021-03-03", "sf_trade_value": 1692.0}, {"date": "2021-03-10", "sf_trade_value": 1515.0}, {"date": "2021-03-17", "sf_trade_value": 1631.0}, {"date": "2021-03-24", "sf_trade_value": 1600.0}, {"date": "2021-03-31", "sf_trade_value": 1530.0}, {"date": "2021-04-07", "sf_trade_value": 1554.0}, {"date": "2021-04-14", "sf_trade_value": 1656.0}, {"date": "2021-04-15", "sf_trade_value": 1656.0}]